{".class": "MypyFile", "_fullname": "core", "_name": null, "is_stub": false, "names": {".class": "SymbolTable", "Character": {".class": "SymbolTableNode", "kind": "Gdef", "node": {".class": "TypeInfo", "_promote": null, "abstract_attributes": [], "bases": ["core.Character@4"], "declared_metaclass": null, "defn": {".class": "ClassDef", "fullname": "core.Character", "metaclass": null, "name": "Character", "type_vars": []}, "flags": [], "fullname": "core.Character", "metaclass_type": "abc.ABCMeta", "module_name": "core", "names": {".class": "SymbolTable", "all": {".class": "SymbolTableNode", "kind": "Mdef", "node": {".class": "Decorator", "func": {".class": "FuncDef", "arg_kinds": [], "arg_names": [], "flags": ["is_static", "is_decorated"], "fullname": "core.Character.all", "name": "all", "type": null}, "is_overload": false, "var": {".class": "Var", "flags": ["is_ready", "is_initialized_in_class", "is_staticmethod"], "fullname": null, "name": "all", "type": {".class": "CallableType", "arg_kinds": [], "arg_names": [], "arg_types": [], "bound_args": [], "fallback": "builtins.function", "implicit": true, "is_classmethod_class": false, "is_ellipsis_args": false, "name": "\"all\" of \"Character\"", "ret_type": {".class": "AnyType"}, "variables": []}}}}, "get": {".class": "SymbolTableNode", "kind": "Mdef", "node": {".class": "Decorator", "func": {".class": "FuncDef", "arg_kinds": [0], "arg_names": ["i"], "flags": ["is_static", "is_decorated"], "fullname": "core.Character.get", "name": "get", "type": null}, "is_overload": false, "var": {".class": "Var", "flags": ["is_ready", "is_initialized_in_class", "is_staticmethod"], "fullname": null, "name": "get", "type": {".class": "CallableType", "arg_kinds": [0], "arg_names": ["i"], "arg_types": [{".class": "AnyType"}], "bound_args": [], "fallback": "builtins.function", "implicit": true, "is_classmethod_class": false, "is_ellipsis_args": false, "name": "\"get\" of \"Character\"", "ret_type": {".class": "AnyType"}, "variables": []}}}}}, "tuple_type": {".class": "TupleType", "fallback": "core.Character@4", "implicit": false, "items": [{".class": "AnyType"}, {".class": "AnyType"}, {".class": "AnyType"}, {".class": "AnyType"}, {".class": "AnyType"}]}, "type_vars": [], "typeddict_type": null}}, "Character@4": {".class": "SymbolTableNode", "kind": "Gdef", "node": {".class": "TypeInfo", "_promote": null, "abstract_attributes": [], "bases": [{".class": "Instance", "args": [{".class": "AnyType"}], "type_ref": "builtins.tuple"}], "declared_metaclass": null, "defn": {".class": "ClassDef", "fullname": "core.Character@4", "metaclass": null, "name": "Character@4", "type_vars": []}, "flags": ["is_named_tuple"], "fullname": "core.Character@4", "metaclass_type": null, "module_name": "core", "names": {".class": "SymbolTable", "__annotations__": {".class": "SymbolTableNode", "kind": "Mdef", "node": {".class": "Var", "flags": ["is_ready", "is_initialized_in_class"], "fullname": null, "name": "__annotations__", "type": {".class": "Instance", "args": ["builtins.str", {".class": "AnyType"}], "type_ref": "builtins.dict"}}}, "__doc__": {".class": "SymbolTableNode", "kind": "Mdef", "node": {".class": "Var", "flags": ["is_ready", "is_initialized_in_class"], "fullname": null, "name": "__doc__", "type": "builtins.str"}}, "__init__": {".class": "SymbolTableNode", "kind": "Mdef", "node": {".class": "FuncDef", "arg_kinds": [0, 0, 0, 0, 0, 0], "arg_names": ["self", "name", "type", "age", "img_path", "description"], "flags": [], "fullname": null, "name": "__init__", "type": {".class": "CallableType", "arg_kinds": [0, 0, 0, 0, 0, 0], "arg_names": ["self", "name", "type", "age", "img_path", "description"], "arg_types": [{".class": "TypeVarType", "id": 1, "name": "NT", "upper_bound": {".class": "TupleType", "fallback": {".class": "Instance", "args": [{".class": "AnyType"}], "type_ref": "builtins.tuple"}, "implicit": false, "items": [{".class": "AnyType"}, {".class": "AnyType"}, {".class": "AnyType"}, {".class": "AnyType"}, {".class": "AnyType"}]}, "values": [], "variance": 0}, {".class": "AnyType"}, {".class": "AnyType"}, {".class": "AnyType"}, {".class": "AnyType"}, {".class": "AnyType"}], "bound_args": [], "fallback": "builtins.function", "implicit": false, "is_classmethod_class": false, "is_ellipsis_args": false, "name": "Character@4", "ret_type": {".class": "NoneTyp"}, "variables": [{".class": "TypeVarDef", "id": 1, "name": "NT", "upper_bound": {".class": "TupleType", "fallback": {".class": "Instance", "args": [{".class": "AnyType"}], "type_ref": "builtins.tuple"}, "implicit": false, "items": [{".class": "AnyType"}, {".class": "AnyType"}, {".class": "AnyType"}, {".class": "AnyType"}, {".class": "AnyType"}]}, "values": [], "variance": 0}]}}}, "_asdict": {".class": "SymbolTableNode", "kind": "Mdef", "node": {".class": "FuncDef", "arg_kinds": [0], "arg_names": ["self"], "flags": [], "fullname": null, "name": "_asdict", "type": {".class": "CallableType", "arg_kinds": [0], "arg_names": ["self"], "arg_types": [{".class": "TypeVarType", "id": 1, "name": "NT", "upper_bound": {".class": "TupleType", "fallback": {".class": "Instance", "args": [{".class": "AnyType"}], "type_ref": "builtins.tuple"}, "implicit": false, "items": [{".class": "AnyType"}, {".class": "AnyType"}, {".class": "AnyType"}, {".class": "AnyType"}, {".class": "AnyType"}]}, "values": [], "variance": 0}], "bound_args": [], "fallback": "builtins.function", "implicit": false, "is_classmethod_class": false, "is_ellipsis_args": false, "name": "Character@4._asdict", "ret_type": {".class": "Instance", "args": ["builtins.str", {".class": "AnyType"}], "type_ref": "builtins.dict"}, "variables": [{".class": "TypeVarDef", "id": 1, "name": "NT", "upper_bound": {".class": "TupleType", "fallback": {".class": "Instance", "args": [{".class": "AnyType"}], "type_ref": "builtins.tuple"}, "implicit": false, "items": [{".class": "AnyType"}, {".class": "AnyType"}, {".class": "AnyType"}, {".class": "AnyType"}, {".class": "AnyType"}]}, "values": [], "variance": 0}]}}}, "_field_defaults": {".class": "SymbolTableNode", "kind": "Mdef", "node": {".class": "Var", "flags": ["is_ready", "is_initialized_in_class"], "fullname": null, "name": "_field_defaults", "type": {".class": "Instance", "args": ["builtins.str", {".class": "AnyType"}], "type_ref": "builtins.dict"}}}, "_field_types": {".class": "SymbolTableNode", "kind": "Mdef", "node": {".class": "Var", "flags": ["is_ready", "is_initialized_in_class"], "fullname": null, "name": "_field_types", "type": {".class": "Instance", "args": ["builtins.str", {".class": "AnyType"}], "type_ref": "builtins.dict"}}}, "_fields": {".class": "SymbolTableNode", "kind": "Mdef", "node": {".class": "Var", "flags": ["is_ready", "is_initialized_in_class"], "fullname": null, "name": "_fields", "type": {".class": "TupleType", "fallback": {".class": "Instance", "args": [{".class": "AnyType"}], "type_ref": "builtins.tuple"}, "implicit": false, "items": ["builtins.str", "builtins.str", "builtins.str", "builtins.str", "builtins.str"]}}}, "_make": {".class": "SymbolTableNode", "kind": "Mdef", "node": {".class": "Decorator", "func": {".class": "FuncDef", "arg_kinds": [0, 0, 5, 5], "arg_names": ["cls", "iterable", "new", "len"], "flags": ["is_class"], "fullname": null, "name": "_make", "type": {".class": "CallableType", "arg_kinds": [0, 0, 5, 5], "arg_names": ["cls", "iterable", "new", "len"], "arg_types": [{".class": "TypeType", "item": {".class": "TypeVarType", "id": 1, "name": "NT", "upper_bound": {".class": "TupleType", "fallback": {".class": "Instance", "args": [{".class": "AnyType"}], "type_ref": "builtins.tuple"}, "implicit": false, "items": [{".class": "AnyType"}, {".class": "AnyType"}, {".class": "AnyType"}, {".class": "AnyType"}, {".class": "AnyType"}]}, "values": [], "variance": 0}}, {".class": "Instance", "args": [{".class": "AnyType"}], "type_ref": "typing.Iterable"}, {".class": "AnyType"}, {".class": "AnyType"}], "bound_args": [], "fallback": "builtins.function", "implicit": false, "is_classmethod_class": false, "is_ellipsis_args": false, "name": "Character@4._make", "ret_type": {".class": "TypeVarType", "id": 1, "name": "NT", "upper_bound": {".class": "TupleType", "fallback": {".class": "Instance", "args": [{".class": "AnyType"}], "type_ref": "builtins.tuple"}, "implicit": false, "items": [{".class": "AnyType"}, {".class": "AnyType"}, {".class": "AnyType"}, {".class": "AnyType"}, {".class": "AnyType"}]}, "values": [], "variance": 0}, "variables": [{".class": "TypeVarDef", "id": 1, "name": "NT", "upper_bound": {".class": "TupleType", "fallback": {".class": "Instance", "args": [{".class": "AnyType"}], "type_ref": "builtins.tuple"}, "implicit": false, "items": [{".class": "AnyType"}, {".class": "AnyType"}, {".class": "AnyType"}, {".class": "AnyType"}, {".class": "AnyType"}]}, "values": [], "variance": 0}]}}, "is_overload": false, "var": {".class": "Var", "flags": ["is_ready", "is_classmethod"], "fullname": null, "name": "_make", "type": {".class": "CallableType", "arg_kinds": [0, 0, 5, 5], "arg_names": ["cls", "iterable", "new", "len"], "arg_types": [{".class": "TypeType", "item": {".class": "TypeVarType", "id": 1, "name": "NT", "upper_bound": {".class": "TupleType", "fallback": {".class": "Instance", "args": [{".class": "AnyType"}], "type_ref": "builtins.tuple"}, "implicit": false, "items": [{".class": "AnyType"}, {".class": "AnyType"}, {".class": "AnyType"}, {".class": "AnyType"}, {".class": "AnyType"}]}, "values": [], "variance": 0}}, {".class": "Instance", "args": [{".class": "AnyType"}], "type_ref": "typing.Iterable"}, {".class": "AnyType"}, {".class": "AnyType"}], "bound_args": [], "fallback": "builtins.function", "implicit": false, "is_classmethod_class": false, "is_ellipsis_args": false, "name": "Character@4._make", "ret_type": {".class": "TypeVarType", "id": 1, "name": "NT", "upper_bound": {".class": "TupleType", "fallback": {".class": "Instance", "args": [{".class": "AnyType"}], "type_ref": "builtins.tuple"}, "implicit": false, "items": [{".class": "AnyType"}, {".class": "AnyType"}, {".class": "AnyType"}, {".class": "AnyType"}, {".class": "AnyType"}]}, "values": [], "variance": 0}, "variables": [{".class": "TypeVarDef", "id": 1, "name": "NT", "upper_bound": {".class": "TupleType", "fallback": {".class": "Instance", "args": [{".class": "AnyType"}], "type_ref": "builtins.tuple"}, "implicit": false, "items": [{".class": "AnyType"}, {".class": "AnyType"}, {".class": "AnyType"}, {".class": "AnyType"}, {".class": "AnyType"}]}, "values": [], "variance": 0}]}}}}, "_replace": {".class": "SymbolTableNode", "kind": "Mdef", "node": {".class": "FuncDef", "arg_kinds": [0, 5, 5, 5, 5, 5], "arg_names": ["self", "name", "type", "age", "img_path", "description"], "flags": [], "fullname": null, "name": "_replace", "type": {".class": "CallableType", "arg_kinds": [0, 5, 5, 5, 5, 5], "arg_names": ["self", "name", "type", "age", "img_path", "description"], "arg_types": [{".class": "TypeVarType", "id": 1, "name": "NT", "upper_bound": {".class": "TupleType", "fallback": {".class": "Instance", "args": [{".class": "AnyType"}], "type_ref": "builtins.tuple"}, "implicit": false, "items": [{".class": "AnyType"}, {".class": "AnyType"}, {".class": "AnyType"}, {".class": "AnyType"}, {".class": "AnyType"}]}, "values": [], "variance": 0}, {".class": "AnyType"}, {".class": "AnyType"}, {".class": "AnyType"}, {".class": "AnyType"}, {".class": "AnyType"}], "bound_args": [], "fallback": "builtins.function", "implicit": false, "is_classmethod_class": false, "is_ellipsis_args": false, "name": "Character@4._replace", "ret_type": {".class": "TypeVarType", "id": 1, "name": "NT", "upper_bound": {".class": "TupleType", "fallback": {".class": "Instance", "args": [{".class": "AnyType"}], "type_ref": "builtins.tuple"}, "implicit": false, "items": [{".class": "AnyType"}, {".class": "AnyType"}, {".class": "AnyType"}, {".class": "AnyType"}, {".class": "AnyType"}]}, "values": [], "variance": 0}, "variables": [{".class": "TypeVarDef", "id": 1, "name": "NT", "upper_bound": {".class": "TupleType", "fallback": {".class": "Instance", "args": [{".class": "AnyType"}], "type_ref": "builtins.tuple"}, "implicit": false, "items": [{".class": "AnyType"}, {".class": "AnyType"}, {".class": "AnyType"}, {".class": "AnyType"}, {".class": "AnyType"}]}, "values": [], "variance": 0}]}}}, "_source": {".class": "SymbolTableNode", "kind": "Mdef", "node": {".class": "Var", "flags": ["is_ready", "is_initialized_in_class"], "fullname": null, "name": "_source", "type": "builtins.str"}}, "age": {".class": "SymbolTableNode", "kind": "Mdef", "node": {".class": "Var", "flags": ["is_ready", "is_property"], "fullname": null, "name": "age", "type": {".class": "AnyType"}}}, "description": {".class": "SymbolTableNode", "kind": "Mdef", "node": {".class": "Var", "flags": ["is_ready", "is_property"], "fullname": null, "name": "description", "type": {".class": "AnyType"}}}, "img_path": {".class": "SymbolTableNode", "kind": "Mdef", "node": {".class": "Var", "flags": ["is_ready", "is_property"], "fullname": null, "name": "img_path", "type": {".class": "AnyType"}}}, "name": {".class": "SymbolTableNode", "kind": "Mdef", "node": {".class": "Var", "flags": ["is_ready", "is_property"], "fullname": null, "name": "name", "type": {".class": "AnyType"}}}, "type": {".class": "SymbolTableNode", "kind": "Mdef", "node": {".class": "Var", "flags": ["is_ready", "is_property"], "fullname": null, "name": "type", "type": {".class": "AnyType"}}}}, "tuple_type": {".class": "TupleType", "fallback": {".class": "Instance", "args": [{".class": "AnyType"}], "type_ref": "builtins.tuple"}, "implicit": false, "items": [{".class": "AnyType"}, {".class": "AnyType"}, {".class": "AnyType"}, {".class": "AnyType"}, {".class": "AnyType"}]}, "type_vars": [], "typeddict_type": null}}, "_Characters": {".class": "SymbolTableNode", "kind": "Gdef", "node": {".class": "Var", "flags": [], "fullname": "core._Characters", "name": "_Characters", "type": {".class": "Instance", "args": [{".class": "TupleType", "fallback": "core.Character", "implicit": false, "items": [{".class": "AnyType"}, {".class": "AnyType"}, {".class": "AnyType"}, {".class": "AnyType"}, {".class": "AnyType"}]}], "type_ref": "builtins.list"}}}, "__doc__": {".class": "SymbolTableNode", "kind": "Gdef", "node": {".class": "Var", "flags": ["is_ready"], "fullname": "core.__doc__", "name": "__doc__", "type": "builtins.str"}}, "__file__": {".class": "SymbolTableNode", "kind": "Gdef", "node": {".class": "Var", "flags": ["is_ready"], "fullname": "core.__file__", "name": "__file__", "type": "builtins.str"}}, "__name__": {".class": "SymbolTableNode", "kind": "Gdef", "node": {".class": "Var", "flags": ["is_ready"], "fullname": "core.__name__", "name": "__name__", "type": "builtins.str"}}, "__package__": {".class": "SymbolTableNode", "kind": "Gdef", "node": {".class": "Var", "flags": ["is_ready"], "fullname": "core.__package__", "name": "__package__", "type": "builtins.str"}}, "namedtuple": {".class": "SymbolTableNode", "cross_ref": "collections.namedtuple", "kind": "Gdef"}}, "path": "/home/basecamp/RisingWarriors/core.py"}
